[{
    "Name": "Genesys",
    "Initial Investment": "12-2016",
    "Main Industry": "Oil & Gas Consumable Fuels",
    "Commit/Reserves": null,
    "Current ownership": 12.10,
    "Total Investment cost": 7,
    "Current Investment cost": 0.1,
    "Realized": null,
    "Fair Market value": 7,
    "Total Value": 7,
    "Multiples of cost": 1.00,
    "Gross IRR": 72.22
},
{
  "Name": "Treasury Tech",
  "Initial Investment": "12-2017",
  "Main Industry": "Leisure Equipment & Products",
  "Commit/Reserves": null,
  "Current ownership": 10,
  "Total Investment cost": 23,
  "Current Investment cost": 0.5,
  "Realized": 70,
  "Fair Market value": 30,
  "Total Value": 70,
  "Multiples of cost": 1.00,
  "Gross IRR": null
},
{
  "Name": "RS Education",
  "Initial Investment": "12-2018",
  "Main Industry": "Diversified Consumer Services",
  "Commit/Reserves": null,
  "Current ownership": 18.20,
  "Total Investment cost": 42,
  "Current Investment cost": 12,
  "Realized": null,
  "Fair Market value": 12,
  "Total Value": 10,
  "Multiples of cost": 2.00,
  "Gross IRR": 52.00
},
{
  "Name": "SR insurance Technology",
  "Initial Investment": "12-2018",
  "Main Industry": "Insurance",
  "Commit/Reserves": null,
  "Current ownership": 3.4,
  "Total Investment cost": 34,
  "Current Investment cost": 42,
  "Realized": null,
  "Fair Market value": 12,
  "Total Value": 42,
  "Multiples of cost": 4.2,
  "Gross IRR": null
},
{
  "Name": "Syntec Automation",
  "Initial Investment": "12-2019",
  "Main Industry": "Construction Materials",
  "Commit/Reserves": null,
  "Current ownership": 17.50,
  "Total Investment cost": 14,
  "Current Investment cost": 32,
  "Realized": null,
  "Fair Market value": 42,
  "Total Value": 30,
  "Multiples of cost": 3.5,
  "Gross IRR": null
},
{
  "Name": "Tinker Technologies",
  "Initial Investment": "12-2019",
  "Main Industry": "Internet Software & Services",
  "Commit/Reserves": null,
  "Current ownership": 12.78,
  "Total Investment cost": 20,
  "Current Investment cost": 45,
  "Realized": null,
  "Fair Market value": 78,
  "Total Value": 41,
  "Multiples of cost": 1.25,
  "Gross IRR": null
},
{
  "Name": "TSM Healthcare",
  "Initial Investment": "12-2019",
  "Main Industry": "Health Care Equipment & Supplies",
  "Commit/Reserves": null,
  "Current ownership": 14.15,
  "Total Investment cost": 42,
  "Current Investment cost": 50,
  "Realized": null,
  "Fair Market value": 23,
  "Total Value": 45,
  "Multiples of cost": 2.14,
  "Gross IRR": null
},
{
  "Name": "WD",
  "Initial Investment": "01-2020",
  "Main Industry": "Computers & Peripherals",
  "Commit/Reserves": null,
  "Current ownership": 5.75,
  "Total Investment cost": 30,
  "Current Investment cost": 1.2,
  "Realized": null,
  "Fair Market value": 25,
  "Total Value": 45,
  "Multiples of cost": 1.58,
  "Gross IRR": null
}
]
